flax_addons/__init__.py
flax_addons/layers/__init__.py
flax_addons/layers/transformers.py
flax_addons/preprocessing/__init__.py
flax_addons/preprocessing/mel_generator.py
flax_addons/utils/__init__.py
flax_addons/utils/audio.py
flax_addons/utils/cuda/__init__.py
flax_addons/utils/cuda/irfft.py
flax_addons-0.1.1.dist-info/LICENSE
flax_addons-0.1.1.dist-info/WHEEL
flax_addons-0.1.1.dist-info/METADATA
flax_addons-0.1.1.dist-info/RECORD
